dj_anonymizer/__init__.py
dj_anonymizer/anonymizer.py
dj_anonymizer/apps.py
dj_anonymizer/fields.py
dj_anonymizer/register_models.py
dj_anonymizer/utils.py
dj_anonymizer/management/__init__.py
dj_anonymizer/management/commands/__init__.py
dj_anonymizer/management/commands/anonymize_db.py
dj_anonymizer-0.6.1.dist-info/LICENSE.txt
dj_anonymizer-0.6.1.dist-info/METADATA
dj_anonymizer-0.6.1.dist-info/WHEEL
dj_anonymizer-0.6.1.dist-info/top_level.txt
dj_anonymizer-0.6.1.dist-info/RECORD
